{
  "summary": {
    "total_issues": 140,
    "total_files": 54,
    "total_doctypes": 22
  },
  "by_file_type": {
    "test_file": {
      "count": 50,
      "files": 20,
      "doctypes": [
        "Membership Type",
        "Team",
        "Member IBAN History",
        "Member",
        "Membership",
        "Membership Dues Schedule",
        "SEPA Mandate",
        "Chapter Board Member",
        "SEPA Mandate Usage",
        "Communication History",
        "Chapter",
        "Termination Audit Entry",
        "Member Fee Change History"
      ]
    },
    "utility": {
      "count": 25,
      "files": 13,
      "doctypes": [
        "Membership Type",
        "Donation",
        "Volunteer Expense",
        "Member IBAN History",
        "Member",
        "Membership",
        "Team Member",
        "E-Boekhouden Ledger Mapping",
        "Chapter",
        "EBoekhouden REST Mutation Cache"
      ]
    },
    "other": {
      "count": 8,
      "files": 2,
      "doctypes": [
        "Member"
      ]
    },
    "doctype_controller": {
      "count": 54,
      "files": 16,
      "doctypes": [
        "Donation",
        "E-Boekhouden Migration",
        "Chapter Member",
        "Member",
        "Membership Dues Schedule",
        "Membership",
        "Chapter Board Member",
        "Brand Settings",
        "Chapter",
        "Volunteer Activity"
      ]
    },
    "report": {
      "count": 1,
      "files": 1,
      "doctypes": [
        "Member"
      ]
    },
    "debug_script": {
      "count": 2,
      "files": 2,
      "doctypes": [
        "E-Boekhouden Ledger Mapping"
      ]
    }
  },
  "by_doctype": {
    "Communication History": {
      "count": 6,
      "missing_fields": [
        "reference_name",
        "communication_type",
        "reference_doctype"
      ],
      "files_affected": 2
    },
    "Chapter": {
      "count": 9,
      "missing_fields": [
        "chapter_name",
        "status",
        "postal_code_ranges",
        "donation_account",
        "is_active"
      ],
      "files_affected": 4
    },
    "EBoekhouden REST Mutation Cache": {
      "count": 2,
      "missing_fields": [
        "processed",
        "count(*)"
      ],
      "files_affected": 1
    },
    "Member IBAN History": {
      "count": 5,
      "missing_fields": [
        "*"
      ],
      "files_affected": 3
    },
    "Member": {
      "count": 17,
      "missing_fields": [
        "suggested_chapter",
        "chapter",
        "postal_code",
        "city",
        "chapter_assigned_date",
        "mobile_no",
        "country",
        "membership_type",
        "member_name",
        "email_address",
        "address_line1",
        "primary_chapter"
      ],
      "files_affected": 10
    },
    "Membership Type": {
      "count": 3,
      "missing_fields": [
        "currency",
        "subscription_plan",
        "subscription_period"
      ],
      "files_affected": 3
    },
    "Team Member": {
      "count": 2,
      "missing_fields": [
        "user"
      ],
      "files_affected": 1
    },
    "Volunteer Expense": {
      "count": 1,
      "missing_fields": [
        "approval_status"
      ],
      "files_affected": 1
    },
    "Membership": {
      "count": 11,
      "missing_fields": [
        "currency",
        "payment_method",
        "dues_schedule",
        "annual_fee",
        "fee_amount",
        "btw_exemption_type"
      ],
      "files_affected": 5
    },
    "Donation": {
      "count": 12,
      "missing_fields": [
        "status",
        "campaign_reference",
        "donation_date",
        "donor_name",
        "donation_message",
        "btw_exemption_type",
        "anonymous"
      ],
      "files_affected": 4
    },
    "SEPA Mandate": {
      "count": 2,
      "missing_fields": [
        "donor",
        "customer"
      ],
      "files_affected": 2
    },
    "Termination Audit Entry": {
      "count": 2,
      "missing_fields": [
        "termination_request",
        "member"
      ],
      "files_affected": 2
    },
    "Chapter Board Member": {
      "count": 14,
      "missing_fields": [
        "status",
        "chapter",
        "member",
        "parent as chapter",
        "role",
        "chapter_role as role"
      ],
      "files_affected": 5
    },
    "Member Fee Change History": {
      "count": 1,
      "missing_fields": [
        "membership"
      ],
      "files_affected": 1
    },
    "SEPA Mandate Usage": {
      "count": 2,
      "missing_fields": [
        "invoice",
        "mandate"
      ],
      "files_affected": 1
    },
    "Membership Dues Schedule": {
      "count": 29,
      "missing_fields": [
        "effective_date",
        "payment_method",
        "billing_day",
        "amount",
        "current_coverage_start",
        "membership",
        "active_mandate",
        "member.full_name as member_name",
        "current_coverage_end"
      ],
      "files_affected": 4
    },
    "Team": {
      "count": 2,
      "missing_fields": [
        "team_members.volunteer"
      ],
      "files_affected": 1
    },
    "Chapter Member": {
      "count": 4,
      "missing_fields": [
        "parent as chapter",
        "chapter"
      ],
      "files_affected": 4
    },
    "E-Boekhouden Migration": {
      "count": 1,
      "missing_fields": [
        "migration_log"
      ],
      "files_affected": 1
    },
    "Brand Settings": {
      "count": 5,
      "missing_fields": [
        "is_active",
        "settings_name"
      ],
      "files_affected": 1
    },
    "Volunteer Activity": {
      "count": 2,
      "missing_fields": [
        "activity_type as assignment_type",
        "description as reference"
      ],
      "files_affected": 1
    },
    "E-Boekhouden Ledger Mapping": {
      "count": 8,
      "missing_fields": [
        "notes",
        "eboekhouden_code",
        "account_type",
        "ledger_description",
        "is_manual"
      ],
      "files_affected": 5
    }
  },
  "by_issue_type": {
    "filter_field": 55,
    "select_field": 85
  },
  "by_function": {
    "frappe.get_all": 122,
    "frappe.db.get_value": 18
  },
  "most_common_missing_fields": {
    "membership": 16,
    "chapter": 7,
    "member": 6,
    "*": 5,
    "is_active": 5,
    "parent as chapter": 5,
    "status": 4,
    "btw_exemption_type": 4,
    "amount": 4,
    "dues_schedule": 4,
    "chapter_name": 3,
    "campaign_reference": 3,
    "primary_chapter": 3,
    "payment_method": 3,
    "ledger_description": 3,
    "reference_doctype": 2,
    "reference_name": 2,
    "communication_type": 2,
    "email_address": 2,
    "currency": 2
  },
  "critical_user_facing": [],
  "detailed_issues": [
    {
      "file": "tests/test_member_status_transitions_enhanced.py",
      "file_type": "test_file",
      "line": 389,
      "field": "reference_doctype",
      "doctype": "Communication History",
      "context": "audit_entries = frappe.get_all(",
      "issue_type": "filter_field",
      "function": "frappe.get_all"
    },
    {
      "file": "tests/test_member_status_transitions_enhanced.py",
      "file_type": "test_file",
      "line": 389,
      "field": "reference_name",
      "doctype": "Communication History",
      "context": "audit_entries = frappe.get_all(",
      "issue_type": "filter_field",
      "function": "frappe.get_all"
    },
    {
      "file": "tests/test_member_status_transitions_enhanced.py",
      "file_type": "test_file",
      "line": 389,
      "field": "communication_type",
      "doctype": "Communication History",
      "context": "audit_entries = frappe.get_all(",
      "issue_type": "filter_field",
      "function": "frappe.get_all"
    },
    {
      "file": "utils/department_hierarchy.py",
      "file_type": "utility",
      "line": 46,
      "field": "status",
      "doctype": "Chapter",
      "context": "chapters = frappe.get_all(\"Chapter\", filters={\"status\": \"Active\"}, fields=[\"name\", \"chapter_name\"])",
      "issue_type": "filter_field",
      "function": "frappe.get_all"
    },
    {
      "file": "utils/department_hierarchy.py",
      "file_type": "utility",
      "line": 46,
      "field": "chapter_name",
      "doctype": "Chapter",
      "context": "chapters = frappe.get_all(\"Chapter\", filters={\"status\": \"Active\"}, fields=[\"name\", \"chapter_name\"])",
      "issue_type": "select_field",
      "function": "frappe.get_all"
    },
    {
      "file": "utils/department_hierarchy.py",
      "file_type": "utility",
      "line": 177,
      "field": "status",
      "doctype": "Chapter",
      "context": "chapters = frappe.get_all(\"Chapter\", filters={\"status\": \"Active\"})",
      "issue_type": "filter_field",
      "function": "frappe.get_all"
    },
    {
      "file": "utils/nuke_financial_data.py",
      "file_type": "utility",
      "line": 263,
      "field": "processed",
      "doctype": "EBoekhouden REST Mutation Cache",
      "context": "f\"   \u2713 Reset {frappe.db.get_value('EBoekhouden REST Mutation Cache', {'processed': 0}, 'count(*)')} mutation cache entries\"",
      "issue_type": "filter_field",
      "function": "frappe.db.get_value"
    },
    {
      "file": "utils/nuke_financial_data.py",
      "file_type": "utility",
      "line": 263,
      "field": "count(*)",
      "doctype": "EBoekhouden REST Mutation Cache",
      "context": "f\"   \u2713 Reset {frappe.db.get_value('EBoekhouden REST Mutation Cache', {'processed': 0}, 'count(*)')} mutation cache entries\"",
      "issue_type": "select_field",
      "function": "frappe.db.get_value"
    },
    {
      "file": "utils/donation_emails.py",
      "file_type": "utility",
      "line": 168,
      "field": "chapter_name",
      "doctype": "Chapter",
      "context": "chapter_name = frappe.db.get_value(\"Chapter\", donation.chapter_reference, \"chapter_name\")",
      "issue_type": "select_field",
      "function": "frappe.db.get_value"
    },
    {
      "file": "utils/iban_history_manager.py",
      "file_type": "utility",
      "line": 84,
      "field": "*",
      "doctype": "Member IBAN History",
      "context": "history = frappe.get_all(",
      "issue_type": "select_field",
      "function": "frappe.get_all"
    },
    {
      "file": "utils/application_notifications.py",
      "file_type": "utility",
      "line": 377,
      "field": "membership_type",
      "doctype": "Member",
      "context": "overdue = frappe.get_all(",
      "issue_type": "select_field",
      "function": "frappe.get_all"
    },
    {
      "file": "utils/portal_customization.py",
      "file_type": "utility",
      "line": 296,
      "field": "email_address",
      "doctype": "Member",
      "context": "member = frappe.get_all(",
      "issue_type": "filter_field",
      "function": "frappe.get_all"
    },
    {
      "file": "utils/portal_customization.py",
      "file_type": "utility",
      "line": 296,
      "field": "email_address",
      "doctype": "Member",
      "context": "member = frappe.get_all(",
      "issue_type": "select_field",
      "function": "frappe.get_all"
    },
    {
      "file": "utils/application_helpers.py",
      "file_type": "utility",
      "line": 92,
      "field": "currency",
      "doctype": "Membership Type",
      "context": "membership_types = frappe.get_all(",
      "issue_type": "select_field",
      "function": "frappe.get_all"
    },
    {
      "file": "utils/dd_security_enhancements.py",
      "file_type": "utility",
      "line": 39,
      "field": "address_line1",
      "doctype": "Member",
      "context": "existing_members = frappe.get_all(",
      "issue_type": "select_field",
      "function": "frappe.get_all"
    },
    {
      "file": "utils/termination_integration.py",
      "file_type": "utility",
      "line": 305,
      "field": "user",
      "doctype": "Team Member",
      "context": "team_memberships = frappe.get_all(",
      "issue_type": "filter_field",
      "function": "frappe.get_all"
    },
    {
      "file": "utils/termination_integration.py",
      "file_type": "utility",
      "line": 305,
      "field": "user",
      "doctype": "Team Member",
      "context": "team_memberships = frappe.get_all(",
      "issue_type": "select_field",
      "function": "frappe.get_all"
    },
    {
      "file": "utils/termination_integration.py",
      "file_type": "utility",
      "line": 678,
      "field": "approval_status",
      "doctype": "Volunteer Expense",
      "context": "active_expenses = frappe.get_all(",
      "issue_type": "filter_field",
      "function": "frappe.get_all"
    },
    {
      "file": "utils/__init__.py",
      "file_type": "utility",
      "line": 413,
      "field": "btw_exemption_type",
      "doctype": "Membership",
      "context": "exemption_type = frappe.db.get_value(\"Membership\", invoice.membership, \"btw_exemption_type\")",
      "issue_type": "select_field",
      "function": "frappe.db.get_value"
    },
    {
      "file": "utils/__init__.py",
      "file_type": "utility",
      "line": 584,
      "field": "btw_exemption_type",
      "doctype": "Membership",
      "context": "frappe.db.get_value(\"Membership\", doc.membership, \"btw_exemption_type\") or \"EXEMPT_MEMBERSHIP\"",
      "issue_type": "select_field",
      "function": "frappe.db.get_value"
    },
    {
      "file": "utils/__init__.py",
      "file_type": "utility",
      "line": 415,
      "field": "btw_exemption_type",
      "doctype": "Donation",
      "context": "exemption_type = frappe.db.get_value(\"Donation\", invoice.donation, \"btw_exemption_type\")",
      "issue_type": "select_field",
      "function": "frappe.db.get_value"
    },
    {
      "file": "utils/__init__.py",
      "file_type": "utility",
      "line": 591,
      "field": "btw_exemption_type",
      "doctype": "Donation",
      "context": "frappe.db.get_value(\"Donation\", doc.donation, \"btw_exemption_type\") or \"EXEMPT_FUNDRAISING\"",
      "issue_type": "select_field",
      "function": "frappe.db.get_value"
    },
    {
      "file": "setup/role_profile_setup.py",
      "file_type": "other",
      "line": 148,
      "field": "member_name",
      "doctype": "Member",
      "context": "members_with_users = frappe.get_all(",
      "issue_type": "select_field",
      "function": "frappe.get_all"
    },
    {
      "file": "tests/fixtures/anbi_test_personas.py",
      "file_type": "test_file",
      "line": 347,
      "field": "donor",
      "doctype": "SEPA Mandate",
      "context": "mandates = frappe.get_all(\"SEPA Mandate\",",
      "issue_type": "filter_field",
      "function": "frappe.get_all"
    },
    {
      "file": "tests/fixtures/enhanced_test_cleanup.py",
      "file_type": "test_file",
      "line": 134,
      "field": "customer",
      "doctype": "SEPA Mandate",
      "context": "for mandate in frappe.get_all(\"SEPA Mandate\", filters={\"customer\": customer_name}):",
      "issue_type": "filter_field",
      "function": "frappe.get_all"
    },
    {
      "file": "tests/utils/assertions.py",
      "file_type": "test_file",
      "line": 197,
      "field": "member",
      "doctype": "Termination Audit Entry",
      "context": "audit_entries = frappe.get_all(\"Termination Audit Entry\", filters={\"member\": member_name})",
      "issue_type": "filter_field",
      "function": "frappe.get_all"
    },
    {
      "file": "tests/backend/security/test_security_comprehensive.py",
      "file_type": "test_file",
      "line": 164,
      "field": "chapter",
      "doctype": "Member",
      "context": "members = frappe.get_all(\"Member\", fields=[\"name\", \"chapter\"])",
      "issue_type": "select_field",
      "function": "frappe.get_all"
    },
    {
      "file": "tests/backend/security/test_security_comprehensive.py",
      "file_type": "test_file",
      "line": 184,
      "field": "annual_fee",
      "doctype": "Membership",
      "context": "frappe.get_all(\"Membership\", fields=[\"annual_fee\", \"member\"])",
      "issue_type": "select_field",
      "function": "frappe.get_all"
    },
    {
      "file": "tests/backend/comprehensive/test_chapter_assignment_comprehensive.py",
      "file_type": "test_file",
      "line": 83,
      "field": "member",
      "doctype": "Chapter Board Member",
      "context": "board_members = frappe.get_all(",
      "issue_type": "filter_field",
      "function": "frappe.get_all"
    },
    {
      "file": "tests/backend/comprehensive/test_chapter_assignment_comprehensive.py",
      "file_type": "test_file",
      "line": 83,
      "field": "status",
      "doctype": "Chapter Board Member",
      "context": "board_members = frappe.get_all(",
      "issue_type": "filter_field",
      "function": "frappe.get_all"
    },
    {
      "file": "tests/backend/comprehensive/test_financial_integration_edge_cases.py",
      "file_type": "test_file",
      "line": 469,
      "field": "membership",
      "doctype": "Member Fee Change History",
      "context": "audit_entries = frappe.get_all(",
      "issue_type": "filter_field",
      "function": "frappe.get_all"
    },
    {
      "file": "tests/backend/comprehensive/test_termination_workflow_edge_cases.py",
      "file_type": "test_file",
      "line": 662,
      "field": "termination_request",
      "doctype": "Termination Audit Entry",
      "context": "audit_entries = frappe.get_all(",
      "issue_type": "filter_field",
      "function": "frappe.get_all"
    },
    {
      "file": "tests/backend/performance/test_api_performance.py",
      "file_type": "test_file",
      "line": 110,
      "field": "chapter",
      "doctype": "Member",
      "context": "members = frappe.get_all(\"Member\",",
      "issue_type": "filter_field",
      "function": "frappe.get_all"
    },
    {
      "file": "tests/backend/components/test_member_lifecycle_iban.py",
      "file_type": "test_file",
      "line": 88,
      "field": "*",
      "doctype": "Member IBAN History",
      "context": "history_records = frappe.get_all(\"Member IBAN History\", filters={\"parent\": member.name}, fields=[\"*\"])",
      "issue_type": "select_field",
      "function": "frappe.get_all"
    },
    {
      "file": "tests/backend/components/test_membership_dues_v2_features.py",
      "file_type": "test_file",
      "line": 647,
      "field": "mandate",
      "doctype": "SEPA Mandate Usage",
      "context": "previous_usage = frappe.get_all(",
      "issue_type": "filter_field",
      "function": "frappe.get_all"
    },
    {
      "file": "tests/backend/components/test_membership_dues_v2_features.py",
      "file_type": "test_file",
      "line": 647,
      "field": "invoice",
      "doctype": "SEPA Mandate Usage",
      "context": "previous_usage = frappe.get_all(",
      "issue_type": "select_field",
      "function": "frappe.get_all"
    },
    {
      "file": "tests/backend/components/test_chapter_assignment_comprehensive.py",
      "file_type": "test_file",
      "line": 483,
      "field": "is_active",
      "doctype": "Chapter",
      "context": "chapters = frappe.get_all(",
      "issue_type": "filter_field",
      "function": "frappe.get_all"
    },
    {
      "file": "tests/backend/components/test_chapter_assignment_comprehensive.py",
      "file_type": "test_file",
      "line": 483,
      "field": "postal_code_ranges",
      "doctype": "Chapter",
      "context": "chapters = frappe.get_all(",
      "issue_type": "select_field",
      "function": "frappe.get_all"
    },
    {
      "file": "tests/backend/components/test_chapter_assignment_comprehensive.py",
      "file_type": "test_file",
      "line": 599,
      "field": "chapter",
      "doctype": "Member",
      "context": "return frappe.get_all(",
      "issue_type": "filter_field",
      "function": "frappe.get_all"
    },
    {
      "file": "tests/backend/components/test_membership_application.py",
      "file_type": "test_file",
      "line": 938,
      "field": "membership",
      "doctype": "Membership Dues Schedule",
      "context": "dues_schedules = frappe.get_all(",
      "issue_type": "filter_field",
      "function": "frappe.get_all"
    },
    {
      "file": "tests/backend/components/test_membership_application.py",
      "file_type": "test_file",
      "line": 994,
      "field": "membership",
      "doctype": "Membership Dues Schedule",
      "context": "dues_schedules = frappe.get_all(",
      "issue_type": "filter_field",
      "function": "frappe.get_all"
    },
    {
      "file": "tests/backend/components/test_membership_application.py",
      "file_type": "test_file",
      "line": 1046,
      "field": "membership",
      "doctype": "Membership Dues Schedule",
      "context": "dues_schedules = frappe.get_all(",
      "issue_type": "filter_field",
      "function": "frappe.get_all"
    },
    {
      "file": "tests/backend/components/test_membership_application.py",
      "file_type": "test_file",
      "line": 1137,
      "field": "membership",
      "doctype": "Membership Dues Schedule",
      "context": "dues_schedules = frappe.get_all(",
      "issue_type": "filter_field",
      "function": "frappe.get_all"
    },
    {
      "file": "tests/backend/components/test_membership_application.py",
      "file_type": "test_file",
      "line": 1441,
      "field": "membership",
      "doctype": "Membership Dues Schedule",
      "context": "dues_schedules = frappe.get_all(",
      "issue_type": "filter_field",
      "function": "frappe.get_all"
    },
    {
      "file": "tests/backend/components/test_membership_application.py",
      "file_type": "test_file",
      "line": 1508,
      "field": "membership",
      "doctype": "Membership Dues Schedule",
      "context": "dues_schedules = frappe.get_all(",
      "issue_type": "filter_field",
      "function": "frappe.get_all"
    },
    {
      "file": "tests/backend/components/test_membership_application.py",
      "file_type": "test_file",
      "line": 1558,
      "field": "membership",
      "doctype": "Membership Dues Schedule",
      "context": "dues_schedules1 = frappe.get_all(",
      "issue_type": "filter_field",
      "function": "frappe.get_all"
    },
    {
      "file": "tests/backend/components/test_membership_application.py",
      "file_type": "test_file",
      "line": 1579,
      "field": "membership",
      "doctype": "Membership Dues Schedule",
      "context": "dues_schedules2 = frappe.get_all(",
      "issue_type": "filter_field",
      "function": "frappe.get_all"
    },
    {
      "file": "tests/backend/components/test_membership_application.py",
      "file_type": "test_file",
      "line": 1673,
      "field": "membership",
      "doctype": "Membership Dues Schedule",
      "context": "dues_schedules = frappe.get_all(",
      "issue_type": "filter_field",
      "function": "frappe.get_all"
    },
    {
      "file": "tests/backend/components/test_membership_application.py",
      "file_type": "test_file",
      "line": 1762,
      "field": "membership",
      "doctype": "Membership Dues Schedule",
      "context": "dues_schedules = frappe.get_all(",
      "issue_type": "filter_field",
      "function": "frappe.get_all"
    },
    {
      "file": "tests/backend/components/test_membership_application.py",
      "file_type": "test_file",
      "line": 1812,
      "field": "membership",
      "doctype": "Membership Dues Schedule",
      "context": "dues_schedules2 = frappe.get_all(",
      "issue_type": "filter_field",
      "function": "frappe.get_all"
    },
    {
      "file": "tests/backend/components/test_membership_application.py",
      "file_type": "test_file",
      "line": 719,
      "field": "membership",
      "doctype": "Membership Dues Schedule",
      "context": "dues_schedules = frappe.get_all(",
      "issue_type": "filter_field",
      "function": "frappe.get_all"
    },
    {
      "file": "tests/backend/components/test_membership_application.py",
      "file_type": "test_file",
      "line": 795,
      "field": "membership",
      "doctype": "Membership Dues Schedule",
      "context": "dues_schedules = frappe.get_all(",
      "issue_type": "filter_field",
      "function": "frappe.get_all"
    },
    {
      "file": "tests/backend/components/test_membership_application.py",
      "file_type": "test_file",
      "line": 795,
      "field": "effective_date",
      "doctype": "Membership Dues Schedule",
      "context": "dues_schedules = frappe.get_all(",
      "issue_type": "select_field",
      "function": "frappe.get_all"
    },
    {
      "file": "tests/backend/components/test_membership_application.py",
      "file_type": "test_file",
      "line": 864,
      "field": "membership",
      "doctype": "Membership Dues Schedule",
      "context": "dues_schedules = frappe.get_all(",
      "issue_type": "filter_field",
      "function": "frappe.get_all"
    },
    {
      "file": "tests/backend/components/test_termination_impact.py",
      "file_type": "test_file",
      "line": 59,
      "field": "role",
      "doctype": "Chapter Board Member",
      "context": "board_positions = frappe.get_all(",
      "issue_type": "select_field",
      "function": "frappe.get_all"
    },
    {
      "file": "tests/backend/components/test_termination_impact.py",
      "file_type": "test_file",
      "line": 59,
      "field": "chapter",
      "doctype": "Chapter Board Member",
      "context": "board_positions = frappe.get_all(",
      "issue_type": "select_field",
      "function": "frappe.get_all"
    },
    {
      "file": "tests/backend/components/test_termination_impact.py",
      "file_type": "test_file",
      "line": 71,
      "field": "member",
      "doctype": "Chapter Board Member",
      "context": "direct_positions = frappe.get_all(",
      "issue_type": "filter_field",
      "function": "frappe.get_all"
    },
    {
      "file": "tests/backend/components/test_termination_impact.py",
      "file_type": "test_file",
      "line": 71,
      "field": "role",
      "doctype": "Chapter Board Member",
      "context": "direct_positions = frappe.get_all(",
      "issue_type": "select_field",
      "function": "frappe.get_all"
    },
    {
      "file": "tests/backend/components/test_termination_impact.py",
      "file_type": "test_file",
      "line": 71,
      "field": "chapter",
      "doctype": "Chapter Board Member",
      "context": "direct_positions = frappe.get_all(",
      "issue_type": "select_field",
      "function": "frappe.get_all"
    },
    {
      "file": "tests/backend/components/test_member_iban_history.py",
      "file_type": "test_file",
      "line": 72,
      "field": "*",
      "doctype": "Member IBAN History",
      "context": "history_records = frappe.get_all(\"Member IBAN History\", filters={\"parent\": member.name}, fields=[\"*\"])",
      "issue_type": "select_field",
      "function": "frappe.get_all"
    },
    {
      "file": "tests/backend/components/test_member_iban_history.py",
      "file_type": "test_file",
      "line": 123,
      "field": "*",
      "doctype": "Member IBAN History",
      "context": "history_records = frappe.get_all(",
      "issue_type": "select_field",
      "function": "frappe.get_all"
    },
    {
      "file": "tests/backend/components/test_member_iban_history.py",
      "file_type": "test_file",
      "line": 229,
      "field": "*",
      "doctype": "Member IBAN History",
      "context": "history_records = frappe.get_all(\"Member IBAN History\", filters={\"parent\": member.name}, fields=[\"*\"])",
      "issue_type": "select_field",
      "function": "frappe.get_all"
    },
    {
      "file": "tests/backend/components/test_membership_utilities.py",
      "file_type": "test_file",
      "line": 332,
      "field": "subscription_plan",
      "doctype": "Membership Type",
      "context": "test_types = frappe.get_all(",
      "issue_type": "select_field",
      "function": "frappe.get_all"
    },
    {
      "file": "tests/backend/components/test_member_status_transitions.py",
      "file_type": "test_file",
      "line": 361,
      "field": "reference_doctype",
      "doctype": "Communication History",
      "context": "audit_entries = frappe.get_all(",
      "issue_type": "filter_field",
      "function": "frappe.get_all"
    },
    {
      "file": "tests/backend/components/test_member_status_transitions.py",
      "file_type": "test_file",
      "line": 361,
      "field": "reference_name",
      "doctype": "Communication History",
      "context": "audit_entries = frappe.get_all(",
      "issue_type": "filter_field",
      "function": "frappe.get_all"
    },
    {
      "file": "tests/backend/components/test_member_status_transitions.py",
      "file_type": "test_file",
      "line": 361,
      "field": "communication_type",
      "doctype": "Communication History",
      "context": "audit_entries = frappe.get_all(",
      "issue_type": "filter_field",
      "function": "frappe.get_all"
    },
    {
      "file": "tests/backend/components/test_fee_override_integration.py",
      "file_type": "test_file",
      "line": 306,
      "field": "effective_date",
      "doctype": "Membership Dues Schedule",
      "context": "dues_history = frappe.get_all(",
      "issue_type": "select_field",
      "function": "frappe.get_all"
    },
    {
      "file": "tests/backend/components/test_payment_interval_fix.py",
      "file_type": "test_file",
      "line": 13,
      "field": "subscription_period",
      "doctype": "Membership Type",
      "context": "membership_types = frappe.get_all(",
      "issue_type": "select_field",
      "function": "frappe.get_all"
    },
    {
      "file": "tests/backend/workflows/test_volunteer_journey.py",
      "file_type": "test_file",
      "line": 562,
      "field": "team_members.volunteer",
      "doctype": "Team",
      "context": "teams = frappe.get_all(\"Team\", filters={\"team_members.volunteer\": volunteer_name}, fields=[\"name\"])",
      "issue_type": "filter_field",
      "function": "frappe.get_all"
    },
    {
      "file": "tests/backend/workflows/test_volunteer_journey.py",
      "file_type": "test_file",
      "line": 535,
      "field": "team_members.volunteer",
      "doctype": "Team",
      "context": "teams = frappe.get_all(",
      "issue_type": "filter_field",
      "function": "frappe.get_all"
    },
    {
      "file": "verenigingen/doctype/donation_campaign/donation_campaign.py",
      "file_type": "doctype_controller",
      "line": 97,
      "field": "donor_name",
      "doctype": "Donation",
      "context": "donations = frappe.get_all(",
      "issue_type": "select_field",
      "function": "frappe.get_all"
    },
    {
      "file": "verenigingen/doctype/donation_campaign/donation_campaign.py",
      "file_type": "doctype_controller",
      "line": 97,
      "field": "anonymous",
      "doctype": "Donation",
      "context": "donations = frappe.get_all(",
      "issue_type": "select_field",
      "function": "frappe.get_all"
    },
    {
      "file": "verenigingen/doctype/donation_campaign/donation_campaign.py",
      "file_type": "doctype_controller",
      "line": 97,
      "field": "donation_message",
      "doctype": "Donation",
      "context": "donations = frappe.get_all(",
      "issue_type": "select_field",
      "function": "frappe.get_all"
    },
    {
      "file": "verenigingen/doctype/donation_campaign/donation_campaign.py",
      "file_type": "doctype_controller",
      "line": 34,
      "field": "anonymous",
      "doctype": "Donation",
      "context": "donations = frappe.get_all(",
      "issue_type": "select_field",
      "function": "frappe.get_all"
    },
    {
      "file": "verenigingen/doctype/donation/donation.py",
      "file_type": "doctype_controller",
      "line": 605,
      "field": "campaign_reference",
      "doctype": "Donation",
      "context": "donations = frappe.get_all(",
      "issue_type": "select_field",
      "function": "frappe.get_all"
    },
    {
      "file": "verenigingen/doctype/donation/donation.py",
      "file_type": "doctype_controller",
      "line": 691,
      "field": "campaign_reference",
      "doctype": "Donation",
      "context": "donations = frappe.get_all(",
      "issue_type": "select_field",
      "function": "frappe.get_all"
    },
    {
      "file": "verenigingen/doctype/donation/donation.py",
      "file_type": "doctype_controller",
      "line": 794,
      "field": "campaign_reference",
      "doctype": "Donation",
      "context": "donations = frappe.get_all(",
      "issue_type": "select_field",
      "function": "frappe.get_all"
    },
    {
      "file": "verenigingen/doctype/donation/donation.py",
      "file_type": "doctype_controller",
      "line": 209,
      "field": "donation_account",
      "doctype": "Chapter",
      "context": "chapter_account = frappe.db.get_value(\"Chapter\", self.chapter_reference, \"donation_account\")",
      "issue_type": "select_field",
      "function": "frappe.db.get_value"
    },
    {
      "file": "verenigingen/doctype/donation/donation.py",
      "file_type": "doctype_controller",
      "line": 274,
      "field": "donation_account",
      "doctype": "Chapter",
      "context": "to_account = frappe.db.get_value(\"Chapter\", self.chapter_reference, \"donation_account\")",
      "issue_type": "select_field",
      "function": "frappe.db.get_value"
    },
    {
      "file": "verenigingen/doctype/donation/donation.py",
      "file_type": "doctype_controller",
      "line": 168,
      "field": "chapter_name",
      "doctype": "Chapter",
      "context": "chapter_name = frappe.db.get_value(\"Chapter\", self.chapter_reference, \"chapter_name\")",
      "issue_type": "select_field",
      "function": "frappe.db.get_value"
    },
    {
      "file": "verenigingen/doctype/membership_termination_request/membership_termination_analytics.py",
      "file_type": "doctype_controller",
      "line": 151,
      "field": "primary_chapter",
      "doctype": "Member",
      "context": "member_chapter = frappe.db.get_value(\"Member\", termination.member, \"primary_chapter\")",
      "issue_type": "select_field",
      "function": "frappe.db.get_value"
    },
    {
      "file": "verenigingen/doctype/volunteer_expense/test_volunteer_expense_fixed.py",
      "file_type": "doctype_controller",
      "line": 488,
      "field": "chapter",
      "doctype": "Chapter Member",
      "context": "chapter_members = frappe.get_all(",
      "issue_type": "filter_field",
      "function": "frappe.get_all"
    },
    {
      "file": "verenigingen/doctype/volunteer_expense/test_volunteer_expense_minimal.py",
      "file_type": "doctype_controller",
      "line": 426,
      "field": "chapter",
      "doctype": "Chapter Member",
      "context": "chapter_members = frappe.get_all(",
      "issue_type": "filter_field",
      "function": "frappe.get_all"
    },
    {
      "file": "verenigingen/doctype/e_boekhouden_migration/e_boekhouden_migration_original_backup.py",
      "file_type": "doctype_controller",
      "line": 6560,
      "field": "migration_log",
      "doctype": "E-Boekhouden Migration",
      "context": "migrations = frappe.get_all(",
      "issue_type": "select_field",
      "function": "frappe.get_all"
    },
    {
      "file": "verenigingen/doctype/contribution_amendment_request/contribution_amendment_request.py",
      "file_type": "doctype_controller",
      "line": 138,
      "field": "amount",
      "doctype": "Membership Dues Schedule",
      "context": "active_dues_schedule = frappe.db.get_value(",
      "issue_type": "select_field",
      "function": "frappe.db.get_value"
    },
    {
      "file": "verenigingen/doctype/contribution_amendment_request/contribution_amendment_request.py",
      "file_type": "doctype_controller",
      "line": 1812,
      "field": "amount",
      "doctype": "Membership Dues Schedule",
      "context": "active_dues_schedule = frappe.db.get_value(",
      "issue_type": "select_field",
      "function": "frappe.db.get_value"
    },
    {
      "file": "verenigingen/doctype/membership_dues_schedule/membership_dues_schedule.py",
      "file_type": "doctype_controller",
      "line": 255,
      "field": "member",
      "doctype": "Chapter Board Member",
      "context": "board_member = frappe.db.get_value(",
      "issue_type": "filter_field",
      "function": "frappe.db.get_value"
    },
    {
      "file": "verenigingen/doctype/direct_debit_batch/enhanced_sepa_processor.py",
      "file_type": "doctype_controller",
      "line": 472,
      "field": "payment_method",
      "doctype": "Membership Dues Schedule",
      "context": "schedules = frappe.get_all(",
      "issue_type": "filter_field",
      "function": "frappe.get_all"
    },
    {
      "file": "verenigingen/doctype/direct_debit_batch/enhanced_sepa_processor.py",
      "file_type": "doctype_controller",
      "line": 472,
      "field": "member.full_name as member_name",
      "doctype": "Membership Dues Schedule",
      "context": "schedules = frappe.get_all(",
      "issue_type": "select_field",
      "function": "frappe.get_all"
    },
    {
      "file": "verenigingen/doctype/direct_debit_batch/enhanced_sepa_processor.py",
      "file_type": "doctype_controller",
      "line": 472,
      "field": "amount",
      "doctype": "Membership Dues Schedule",
      "context": "schedules = frappe.get_all(",
      "issue_type": "select_field",
      "function": "frappe.get_all"
    },
    {
      "file": "verenigingen/doctype/direct_debit_batch/enhanced_sepa_processor.py",
      "file_type": "doctype_controller",
      "line": 472,
      "field": "current_coverage_start",
      "doctype": "Membership Dues Schedule",
      "context": "schedules = frappe.get_all(",
      "issue_type": "select_field",
      "function": "frappe.get_all"
    },
    {
      "file": "verenigingen/doctype/direct_debit_batch/enhanced_sepa_processor.py",
      "file_type": "doctype_controller",
      "line": 472,
      "field": "current_coverage_end",
      "doctype": "Membership Dues Schedule",
      "context": "schedules = frappe.get_all(",
      "issue_type": "select_field",
      "function": "frappe.get_all"
    },
    {
      "file": "verenigingen/doctype/direct_debit_batch/enhanced_sepa_processor.py",
      "file_type": "doctype_controller",
      "line": 79,
      "field": "membership",
      "doctype": "Membership Dues Schedule",
      "context": "schedules = frappe.get_all(",
      "issue_type": "select_field",
      "function": "frappe.get_all"
    },
    {
      "file": "verenigingen/doctype/direct_debit_batch/enhanced_sepa_processor.py",
      "file_type": "doctype_controller",
      "line": 79,
      "field": "amount",
      "doctype": "Membership Dues Schedule",
      "context": "schedules = frappe.get_all(",
      "issue_type": "select_field",
      "function": "frappe.get_all"
    },
    {
      "file": "verenigingen/doctype/direct_debit_batch/enhanced_sepa_processor.py",
      "file_type": "doctype_controller",
      "line": 79,
      "field": "active_mandate",
      "doctype": "Membership Dues Schedule",
      "context": "schedules = frappe.get_all(",
      "issue_type": "select_field",
      "function": "frappe.get_all"
    },
    {
      "file": "verenigingen/doctype/direct_debit_batch/enhanced_sepa_processor.py",
      "file_type": "doctype_controller",
      "line": 79,
      "field": "billing_day",
      "doctype": "Membership Dues Schedule",
      "context": "schedules = frappe.get_all(",
      "issue_type": "select_field",
      "function": "frappe.get_all"
    },
    {
      "file": "verenigingen/doctype/direct_debit_batch/enhanced_sepa_processor.py",
      "file_type": "doctype_controller",
      "line": 79,
      "field": "current_coverage_start",
      "doctype": "Membership Dues Schedule",
      "context": "schedules = frappe.get_all(",
      "issue_type": "select_field",
      "function": "frappe.get_all"
    },
    {
      "file": "verenigingen/doctype/direct_debit_batch/enhanced_sepa_processor.py",
      "file_type": "doctype_controller",
      "line": 79,
      "field": "current_coverage_end",
      "doctype": "Membership Dues Schedule",
      "context": "schedules = frappe.get_all(",
      "issue_type": "select_field",
      "function": "frappe.get_all"
    },
    {
      "file": "verenigingen/doctype/membership/scheduler.py",
      "file_type": "doctype_controller",
      "line": 232,
      "field": "payment_method",
      "doctype": "Membership",
      "context": "pending_memberships = frappe.get_all(",
      "issue_type": "filter_field",
      "function": "frappe.get_all"
    },
    {
      "file": "verenigingen/doctype/membership/scheduler.py",
      "file_type": "doctype_controller",
      "line": 232,
      "field": "fee_amount",
      "doctype": "Membership",
      "context": "pending_memberships = frappe.get_all(",
      "issue_type": "select_field",
      "function": "frappe.get_all"
    },
    {
      "file": "verenigingen/doctype/membership/scheduler.py",
      "file_type": "doctype_controller",
      "line": 232,
      "field": "currency",
      "doctype": "Membership",
      "context": "pending_memberships = frappe.get_all(",
      "issue_type": "select_field",
      "function": "frappe.get_all"
    },
    {
      "file": "verenigingen/doctype/membership/enhanced_dues_schedule.py",
      "file_type": "doctype_controller",
      "line": 129,
      "field": "dues_schedule",
      "doctype": "Membership",
      "context": "memberships = frappe.get_all(",
      "issue_type": "filter_field",
      "function": "frappe.get_all"
    },
    {
      "file": "verenigingen/doctype/membership/enhanced_dues_schedule.py",
      "file_type": "doctype_controller",
      "line": 129,
      "field": "dues_schedule",
      "doctype": "Membership",
      "context": "memberships = frappe.get_all(",
      "issue_type": "select_field",
      "function": "frappe.get_all"
    },
    {
      "file": "verenigingen/doctype/membership/enhanced_dues_schedule.py",
      "file_type": "doctype_controller",
      "line": 238,
      "field": "dues_schedule",
      "doctype": "Membership",
      "context": "memberships = frappe.get_all(",
      "issue_type": "filter_field",
      "function": "frappe.get_all"
    },
    {
      "file": "verenigingen/doctype/membership/enhanced_dues_schedule.py",
      "file_type": "doctype_controller",
      "line": 238,
      "field": "dues_schedule",
      "doctype": "Membership",
      "context": "memberships = frappe.get_all(",
      "issue_type": "select_field",
      "function": "frappe.get_all"
    },
    {
      "file": "verenigingen/doctype/brand_settings/brand_settings.py",
      "file_type": "doctype_controller",
      "line": 587,
      "field": "is_active",
      "doctype": "Brand Settings",
      "context": "active_settings = frappe.get_all(\"Brand Settings\", filters={\"is_active\": 1}, limit=1)",
      "issue_type": "filter_field",
      "function": "frappe.get_all"
    },
    {
      "file": "verenigingen/doctype/brand_settings/brand_settings.py",
      "file_type": "doctype_controller",
      "line": 619,
      "field": "is_active",
      "doctype": "Brand Settings",
      "context": "active_brand = frappe.get_all(",
      "issue_type": "filter_field",
      "function": "frappe.get_all"
    },
    {
      "file": "verenigingen/doctype/brand_settings/brand_settings.py",
      "file_type": "doctype_controller",
      "line": 619,
      "field": "settings_name",
      "doctype": "Brand Settings",
      "context": "active_brand = frappe.get_all(",
      "issue_type": "select_field",
      "function": "frappe.get_all"
    },
    {
      "file": "verenigingen/doctype/brand_settings/brand_settings.py",
      "file_type": "doctype_controller",
      "line": 658,
      "field": "is_active",
      "doctype": "Brand Settings",
      "context": "brand_settings = frappe.get_all(",
      "issue_type": "filter_field",
      "function": "frappe.get_all"
    },
    {
      "file": "verenigingen/doctype/brand_settings/brand_settings.py",
      "file_type": "doctype_controller",
      "line": 677,
      "field": "is_active",
      "doctype": "Brand Settings",
      "context": "brand_doc = frappe.get_all(\"Brand Settings\", filters={\"is_active\": 1}, limit=1)",
      "issue_type": "filter_field",
      "function": "frappe.get_all"
    },
    {
      "file": "verenigingen/doctype/member/member.py",
      "file_type": "doctype_controller",
      "line": 1404,
      "field": "parent as chapter",
      "doctype": "Chapter Member",
      "context": "chapter_members = frappe.get_all(",
      "issue_type": "select_field",
      "function": "frappe.get_all"
    },
    {
      "file": "verenigingen/doctype/member/member.py",
      "file_type": "doctype_controller",
      "line": 1416,
      "field": "parent as chapter",
      "doctype": "Chapter Board Member",
      "context": "board_members = frappe.get_all(",
      "issue_type": "select_field",
      "function": "frappe.get_all"
    },
    {
      "file": "verenigingen/doctype/member/member.py",
      "file_type": "doctype_controller",
      "line": 2497,
      "field": "donor_name",
      "doctype": "Donation",
      "context": "return frappe.get_all(",
      "issue_type": "filter_field",
      "function": "frappe.get_all"
    },
    {
      "file": "verenigingen/doctype/member/member.py",
      "file_type": "doctype_controller",
      "line": 2497,
      "field": "donation_date",
      "doctype": "Donation",
      "context": "return frappe.get_all(",
      "issue_type": "select_field",
      "function": "frappe.get_all"
    },
    {
      "file": "verenigingen/doctype/member/member.py",
      "file_type": "doctype_controller",
      "line": 2497,
      "field": "status",
      "doctype": "Donation",
      "context": "return frappe.get_all(",
      "issue_type": "select_field",
      "function": "frappe.get_all"
    },
    {
      "file": "verenigingen/doctype/volunteer/volunteer.py",
      "file_type": "doctype_controller",
      "line": 669,
      "field": "activity_type as assignment_type",
      "doctype": "Volunteer Activity",
      "context": "activity_history = frappe.get_all(",
      "issue_type": "select_field",
      "function": "frappe.get_all"
    },
    {
      "file": "verenigingen/doctype/volunteer/volunteer.py",
      "file_type": "doctype_controller",
      "line": 669,
      "field": "description as reference",
      "doctype": "Volunteer Activity",
      "context": "activity_history = frappe.get_all(",
      "issue_type": "select_field",
      "function": "frappe.get_all"
    },
    {
      "file": "verenigingen/doctype/member/mixins/chapter_mixin.py",
      "file_type": "doctype_controller",
      "line": 38,
      "field": "parent as chapter",
      "doctype": "Chapter Member",
      "context": "member_chapters = frappe.get_all(",
      "issue_type": "select_field",
      "function": "frappe.get_all"
    },
    {
      "file": "verenigingen/doctype/member/mixins/chapter_mixin.py",
      "file_type": "doctype_controller",
      "line": 55,
      "field": "member",
      "doctype": "Chapter Board Member",
      "context": "board_chapters = frappe.get_all(",
      "issue_type": "filter_field",
      "function": "frappe.get_all"
    },
    {
      "file": "verenigingen/doctype/member/mixins/chapter_mixin.py",
      "file_type": "doctype_controller",
      "line": 55,
      "field": "parent as chapter",
      "doctype": "Chapter Board Member",
      "context": "board_chapters = frappe.get_all(",
      "issue_type": "select_field",
      "function": "frappe.get_all"
    },
    {
      "file": "verenigingen/doctype/member/mixins/chapter_mixin.py",
      "file_type": "doctype_controller",
      "line": 84,
      "field": "member",
      "doctype": "Chapter Board Member",
      "context": "board_roles = frappe.get_all(",
      "issue_type": "filter_field",
      "function": "frappe.get_all"
    },
    {
      "file": "verenigingen/doctype/member/mixins/chapter_mixin.py",
      "file_type": "doctype_controller",
      "line": 84,
      "field": "parent as chapter",
      "doctype": "Chapter Board Member",
      "context": "board_roles = frappe.get_all(",
      "issue_type": "select_field",
      "function": "frappe.get_all"
    },
    {
      "file": "verenigingen/doctype/member/mixins/chapter_mixin.py",
      "file_type": "doctype_controller",
      "line": 84,
      "field": "chapter_role as role",
      "doctype": "Chapter Board Member",
      "context": "board_roles = frappe.get_all(",
      "issue_type": "select_field",
      "function": "frappe.get_all"
    },
    {
      "file": "verenigingen/doctype/member/mixins/payment_mixin.py",
      "file_type": "doctype_controller",
      "line": 218,
      "field": "payment_method",
      "doctype": "Membership",
      "context": "memberships = frappe.get_all(",
      "issue_type": "select_field",
      "function": "frappe.get_all"
    },
    {
      "file": "verenigingen/report/recent_chapter_changes/recent_chapter_changes.py",
      "file_type": "report",
      "line": 110,
      "field": "chapter_assigned_date",
      "doctype": "Member",
      "context": "recent_changes = frappe.get_all(",
      "issue_type": "select_field",
      "function": "frappe.get_all"
    },
    {
      "file": "pages/membership_applications/__init__.py",
      "file_type": "other",
      "line": 39,
      "field": "mobile_no",
      "doctype": "Member",
      "context": "applications = frappe.get_all(",
      "issue_type": "select_field",
      "function": "frappe.get_all"
    },
    {
      "file": "pages/membership_applications/__init__.py",
      "file_type": "other",
      "line": 39,
      "field": "suggested_chapter",
      "doctype": "Member",
      "context": "applications = frappe.get_all(",
      "issue_type": "select_field",
      "function": "frappe.get_all"
    },
    {
      "file": "pages/membership_applications/__init__.py",
      "file_type": "other",
      "line": 39,
      "field": "primary_chapter",
      "doctype": "Member",
      "context": "applications = frappe.get_all(",
      "issue_type": "select_field",
      "function": "frappe.get_all"
    },
    {
      "file": "pages/membership_applications/__init__.py",
      "file_type": "other",
      "line": 39,
      "field": "postal_code",
      "doctype": "Member",
      "context": "applications = frappe.get_all(",
      "issue_type": "select_field",
      "function": "frappe.get_all"
    },
    {
      "file": "pages/membership_applications/__init__.py",
      "file_type": "other",
      "line": 39,
      "field": "city",
      "doctype": "Member",
      "context": "applications = frappe.get_all(",
      "issue_type": "select_field",
      "function": "frappe.get_all"
    },
    {
      "file": "pages/membership_applications/__init__.py",
      "file_type": "other",
      "line": 39,
      "field": "country",
      "doctype": "Member",
      "context": "applications = frappe.get_all(",
      "issue_type": "select_field",
      "function": "frappe.get_all"
    },
    {
      "file": "pages/membership_applications/__init__.py",
      "file_type": "other",
      "line": 118,
      "field": "primary_chapter",
      "doctype": "Member",
      "context": "stats[\"recent_approvals\"] = frappe.get_all(",
      "issue_type": "select_field",
      "function": "frappe.get_all"
    },
    {
      "file": "utils/debug/analyze_payment_mutations.py",
      "file_type": "debug_script",
      "line": 223,
      "field": "ledger_description",
      "doctype": "E-Boekhouden Ledger Mapping",
      "context": "mapping = frappe.db.get_value(",
      "issue_type": "select_field",
      "function": "frappe.db.get_value"
    },
    {
      "file": "utils/debug/analyze_payment_api.py",
      "file_type": "debug_script",
      "line": 155,
      "field": "ledger_description",
      "doctype": "E-Boekhouden Ledger Mapping",
      "context": "mapping = frappe.db.get_value(",
      "issue_type": "select_field",
      "function": "frappe.db.get_value"
    },
    {
      "file": "utils/eboekhouden/migration_api.py",
      "file_type": "utility",
      "line": 252,
      "field": "eboekhouden_code",
      "doctype": "E-Boekhouden Ledger Mapping",
      "context": "mappings = frappe.get_all(",
      "issue_type": "select_field",
      "function": "frappe.get_all"
    },
    {
      "file": "utils/eboekhouden/migration_api.py",
      "file_type": "utility",
      "line": 252,
      "field": "account_type",
      "doctype": "E-Boekhouden Ledger Mapping",
      "context": "mappings = frappe.get_all(",
      "issue_type": "select_field",
      "function": "frappe.get_all"
    },
    {
      "file": "utils/eboekhouden/migration_api.py",
      "file_type": "utility",
      "line": 252,
      "field": "is_manual",
      "doctype": "E-Boekhouden Ledger Mapping",
      "context": "mappings = frappe.get_all(",
      "issue_type": "select_field",
      "function": "frappe.get_all"
    },
    {
      "file": "utils/eboekhouden/migration_api.py",
      "file_type": "utility",
      "line": 252,
      "field": "notes",
      "doctype": "E-Boekhouden Ledger Mapping",
      "context": "mappings = frappe.get_all(",
      "issue_type": "select_field",
      "function": "frappe.get_all"
    },
    {
      "file": "utils/eboekhouden/eboekhouden_api.py",
      "file_type": "utility",
      "line": 847,
      "field": "ledger_description",
      "doctype": "E-Boekhouden Ledger Mapping",
      "context": "mapping = frappe.db.get_value(",
      "issue_type": "select_field",
      "function": "frappe.db.get_value"
    },
    {
      "file": "utils/eboekhouden/transaction_utils.py",
      "file_type": "utility",
      "line": 330,
      "field": "eboekhouden_code",
      "doctype": "E-Boekhouden Ledger Mapping",
      "context": "mapping = frappe.db.get_value(",
      "issue_type": "filter_field",
      "function": "frappe.db.get_value"
    }
  ]
}
