[
 {
  "allow_in_quick_entry": 0,
  "allow_on_submit": 0,
  "bold": 0,
  "collapsible": 0,
  "collapsible_depends_on": null,
  "columns": 0,
  "default": null,
  "depends_on": null,
  "description": "Bank transaction references related to this batch",
  "docstatus": 0,
  "doctype": "Custom Field",
  "dt": "Direct Debit Batch",
  "fetch_from": null,
  "fetch_if_empty": 0,
  "fieldname": "custom_related_bank_transactions",
  "fieldtype": "Long Text",
  "hidden": 0,
  "hide_border": 0,
  "hide_days": 0,
  "hide_seconds": 0,
  "ignore_user_permissions": 0,
  "ignore_xss_filter": 0,
  "in_global_search": 0,
  "in_list_view": 0,
  "in_preview": 0,
  "in_standard_filter": 0,
  "insert_after": "custom_reconciliation_status",
  "is_system_generated": 0,
  "is_virtual": 0,
  "label": "Related Bank Transactions",
  "length": 0,
  "link_filters": null,
  "mandatory_depends_on": null,
  "modified": "2025-08-01 20:32:02.221243",
  "module": "Verenigingen",
  "name": "Direct Debit Batch-custom_related_bank_transactions",
  "no_copy": 0,
  "non_negative": 0,
  "options": "",
  "permlevel": 0,
  "placeholder": null,
  "precision": "",
  "print_hide": 0,
  "print_hide_if_no_value": 0,
  "print_width": null,
  "read_only": 0,
  "read_only_depends_on": null,
  "report_hide": 0,
  "reqd": 0,
  "search_index": 0,
  "show_dashboard": 0,
  "sort_options": 0,
  "translatable": 0,
  "unique": 0,
  "width": null
 },
 {
  "allow_in_quick_entry": 0,
  "allow_on_submit": 0,
  "bold": 0,
  "collapsible": 0,
  "collapsible_depends_on": null,
  "columns": 0,
  "default": "",
  "depends_on": null,
  "description": "Related SEPA Direct Debit Batch",
  "docstatus": 0,
  "doctype": "Custom Field",
  "dt": "Bank Transaction",
  "fetch_from": null,
  "fetch_if_empty": 0,
  "fieldname": "custom_sepa_batch",
  "fieldtype": "Link",
  "hidden": 0,
  "hide_border": 0,
  "hide_days": 0,
  "hide_seconds": 0,
  "ignore_user_permissions": 0,
  "ignore_xss_filter": 0,
  "in_global_search": 0,
  "in_list_view": 0,
  "in_preview": 0,
  "in_standard_filter": 0,
  "insert_after": "bank_account",
  "is_system_generated": 0,
  "is_virtual": 0,
  "label": "SEPA Batch",
  "length": 0,
  "link_filters": null,
  "mandatory_depends_on": null,
  "modified": "2025-08-01 20:29:38.644574",
  "module": "Verenigingen",
  "name": "Bank Transaction-custom_sepa_batch",
  "no_copy": 0,
  "non_negative": 0,
  "options": "SEPA Direct Debit Batch",
  "permlevel": 0,
  "placeholder": null,
  "precision": "",
  "print_hide": 0,
  "print_hide_if_no_value": 0,
  "print_width": null,
  "read_only": 0,
  "read_only_depends_on": null,
  "report_hide": 0,
  "reqd": 0,
  "search_index": 0,
  "show_dashboard": 0,
  "sort_options": 0,
  "translatable": 0,
  "unique": 0,
  "width": null
 },
 {
  "allow_in_quick_entry": 0,
  "allow_on_submit": 0,
  "bold": 0,
  "collapsible": 0,
  "collapsible_depends_on": null,
  "columns": 0,
  "default": null,
  "depends_on": "eval:doc.is_membership_invoice",
  "description": "Association member linked to this invoice",
  "docstatus": 0,
  "doctype": "Custom Field",
  "dt": "Sales Invoice",
  "fetch_from": "customer.member",
  "fetch_if_empty": 0,
  "fieldname": "member",
  "fieldtype": "Link",
  "hidden": 0,
  "hide_border": 0,
  "hide_days": 0,
  "hide_seconds": 0,
  "ignore_user_permissions": 0,
  "ignore_xss_filter": 0,
  "in_global_search": 0,
  "in_list_view": 0,
  "in_preview": 0,
  "in_standard_filter": 1,
  "insert_after": "membership",
  "is_system_generated": 1,
  "is_virtual": 0,
  "label": "Member",
  "length": 0,
  "link_filters": null,
  "mandatory_depends_on": null,
  "modified": "2025-08-01 18:21:00.678666",
  "module": "Verenigingen",
  "name": "Sales Invoice-member",
  "no_copy": 0,
  "non_negative": 0,
  "options": "Member",
  "permlevel": 0,
  "placeholder": null,
  "precision": "",
  "print_hide": 0,
  "print_hide_if_no_value": 0,
  "print_width": null,
  "read_only": 1,
  "read_only_depends_on": null,
  "report_hide": 0,
  "reqd": 0,
  "search_index": 0,
  "show_dashboard": 0,
  "sort_options": 0,
  "translatable": 0,
  "unique": 0,
  "width": null
 },
 {
  "allow_in_quick_entry": 0,
  "allow_on_submit": 1,
  "bold": 0,
  "collapsible": 0,
  "collapsible_depends_on": null,
  "columns": 0,
  "default": null,
  "depends_on": "eval:doc.is_membership_invoice",
  "description": "Links invoice to specific membership record",
  "docstatus": 0,
  "doctype": "Custom Field",
  "dt": "Sales Invoice",
  "fetch_from": null,
  "fetch_if_empty": 0,
  "fieldname": "membership",
  "fieldtype": "Link",
  "hidden": 0,
  "hide_border": 0,
  "hide_days": 0,
  "hide_seconds": 0,
  "ignore_user_permissions": 0,
  "ignore_xss_filter": 0,
  "in_global_search": 0,
  "in_list_view": 0,
  "in_preview": 0,
  "in_standard_filter": 0,
  "insert_after": "is_membership_invoice",
  "is_system_generated": 1,
  "is_virtual": 0,
  "label": "Membership",
  "length": 0,
  "link_filters": null,
  "mandatory_depends_on": null,
  "modified": "2025-08-01 18:21:00.585122",
  "module": "Verenigingen",
  "name": "Sales Invoice-membership",
  "no_copy": 1,
  "non_negative": 0,
  "options": "Membership",
  "permlevel": 0,
  "placeholder": null,
  "precision": "",
  "print_hide": 0,
  "print_hide_if_no_value": 0,
  "print_width": null,
  "read_only": 1,
  "read_only_depends_on": null,
  "report_hide": 0,
  "reqd": 0,
  "search_index": 0,
  "show_dashboard": 0,
  "sort_options": 0,
  "translatable": 0,
  "unique": 0,
  "width": null
 },
 {
  "allow_in_quick_entry": 0,
  "allow_on_submit": 0,
  "bold": 0,
  "collapsible": 0,
  "collapsible_depends_on": null,
  "columns": 0,
  "default": "0",
  "depends_on": null,
  "description": null,
  "docstatus": 0,
  "doctype": "Custom Field",
  "dt": "Sales Invoice",
  "fetch_from": null,
  "fetch_if_empty": 0,
  "fieldname": "is_membership_invoice",
  "fieldtype": "Check",
  "hidden": 0,
  "hide_border": 0,
  "hide_days": 0,
  "hide_seconds": 0,
  "ignore_user_permissions": 0,
  "ignore_xss_filter": 0,
  "in_global_search": 0,
  "in_list_view": 0,
  "in_preview": 0,
  "in_standard_filter": 0,
  "insert_after": "membership_dues_section",
  "is_system_generated": 1,
  "is_virtual": 0,
  "label": "Is Membership Invoice",
  "length": 0,
  "link_filters": null,
  "mandatory_depends_on": null,
  "modified": "2025-08-01 18:21:00.446171",
  "module": "Verenigingen",
  "name": "Sales Invoice-is_membership_invoice",
  "no_copy": 0,
  "non_negative": 0,
  "options": null,
  "permlevel": 0,
  "placeholder": null,
  "precision": "",
  "print_hide": 0,
  "print_hide_if_no_value": 0,
  "print_width": null,
  "read_only": 0,
  "read_only_depends_on": null,
  "report_hide": 0,
  "reqd": 0,
  "search_index": 0,
  "show_dashboard": 0,
  "sort_options": 0,
  "translatable": 0,
  "unique": 0,
  "width": null
 },
 {
  "allow_in_quick_entry": 0,
  "allow_on_submit": 0,
  "bold": 0,
  "collapsible": 0,
  "collapsible_depends_on": null,
  "columns": 0,
  "default": null,
  "depends_on": null,
  "description": "Link to original donor record for nonprofit operations",
  "docstatus": 0,
  "doctype": "Custom Field",
  "dt": "Customer",
  "fetch_from": null,
  "fetch_if_empty": 0,
  "fieldname": "custom_donor_reference",
  "fieldtype": "Link",
  "hidden": 0,
  "hide_border": 0,
  "hide_days": 0,
  "hide_seconds": 0,
  "ignore_user_permissions": 0,
  "ignore_xss_filter": 0,
  "in_global_search": 0,
  "in_list_view": 0,
  "in_preview": 0,
  "in_standard_filter": 0,
  "insert_after": "customer_group",
  "is_system_generated": 1,
  "is_virtual": 0,
  "label": "Donor Reference",
  "length": 0,
  "link_filters": null,
  "mandatory_depends_on": null,
  "modified": "2025-07-27 21:55:32.986424",
  "module": "Verenigingen",
  "name": "Customer-custom_donor_reference",
  "no_copy": 0,
  "non_negative": 0,
  "options": "Donor",
  "permlevel": 0,
  "placeholder": null,
  "precision": "",
  "print_hide": 0,
  "print_hide_if_no_value": 0,
  "print_width": null,
  "read_only": 0,
  "read_only_depends_on": null,
  "report_hide": 0,
  "reqd": 0,
  "search_index": 0,
  "show_dashboard": 0,
  "sort_options": 0,
  "translatable": 0,
  "unique": 0,
  "width": null
 },
 {
  "allow_in_quick_entry": 0,
  "allow_on_submit": 0,
  "bold": 0,
  "collapsible": 1,
  "collapsible_depends_on": null,
  "columns": 0,
  "default": null,
  "depends_on": null,
  "description": null,
  "docstatus": 0,
  "doctype": "Custom Field",
  "dt": "Sales Invoice",
  "fetch_from": null,
  "fetch_if_empty": 0,
  "fieldname": "custom_donation_section",
  "fieldtype": "Section Break",
  "hidden": 0,
  "hide_border": 0,
  "hide_days": 0,
  "hide_seconds": 0,
  "ignore_user_permissions": 0,
  "ignore_xss_filter": 0,
  "in_global_search": 0,
  "in_list_view": 0,
  "in_preview": 0,
  "in_standard_filter": 0,
  "insert_after": "btw_reporting_category",
  "is_system_generated": 1,
  "is_virtual": 0,
  "label": "Donation Information",
  "length": 0,
  "link_filters": null,
  "mandatory_depends_on": null,
  "modified": "2025-07-27 21:55:32.985725",
  "module": "Verenigingen",
  "name": "Sales Invoice-custom_donation_section",
  "no_copy": 0,
  "non_negative": 0,
  "options": null,
  "permlevel": 0,
  "placeholder": null,
  "precision": "",
  "print_hide": 0,
  "print_hide_if_no_value": 0,
  "print_width": null,
  "read_only": 0,
  "read_only_depends_on": null,
  "report_hide": 0,
  "reqd": 0,
  "search_index": 0,
  "show_dashboard": 0,
  "sort_options": 0,
  "translatable": 0,
  "unique": 0,
  "width": null
 },
 {
  "allow_in_quick_entry": 0,
  "allow_on_submit": 0,
  "bold": 0,
  "collapsible": 0,
  "collapsible_depends_on": null,
  "columns": 0,
  "default": null,
  "depends_on": null,
  "description": "Original donation record that created this invoice",
  "docstatus": 0,
  "doctype": "Custom Field",
  "dt": "Sales Invoice",
  "fetch_from": null,
  "fetch_if_empty": 0,
  "fieldname": "custom_source_donation",
  "fieldtype": "Link",
  "hidden": 0,
  "hide_border": 0,
  "hide_days": 0,
  "hide_seconds": 0,
  "ignore_user_permissions": 0,
  "ignore_xss_filter": 0,
  "in_global_search": 0,
  "in_list_view": 0,
  "in_preview": 0,
  "in_standard_filter": 0,
  "insert_after": "custom_donation_section",
  "is_system_generated": 1,
  "is_virtual": 0,
  "label": "Source Donation",
  "length": 0,
  "link_filters": null,
  "mandatory_depends_on": null,
  "modified": "2025-07-27 21:55:32.984793",
  "module": "Verenigingen",
  "name": "Sales Invoice-custom_source_donation",
  "no_copy": 0,
  "non_negative": 0,
  "options": "Donation",
  "permlevel": 0,
  "placeholder": null,
  "precision": "",
  "print_hide": 0,
  "print_hide_if_no_value": 0,
  "print_width": null,
  "read_only": 0,
  "read_only_depends_on": null,
  "report_hide": 0,
  "reqd": 0,
  "search_index": 0,
  "show_dashboard": 0,
  "sort_options": 0,
  "translatable": 0,
  "unique": 0,
  "width": null
 },
 {
  "allow_in_quick_entry": 0,
  "allow_on_submit": 0,
  "bold": 0,
  "collapsible": 0,
  "collapsible_depends_on": null,
  "columns": 0,
  "default": null,
  "depends_on": null,
  "description": null,
  "docstatus": 0,
  "doctype": "Custom Field",
  "dt": "Sales Invoice",
  "fetch_from": null,
  "fetch_if_empty": 0,
  "fieldname": "custom_membership_dues_schedule",
  "fieldtype": "Link",
  "hidden": 0,
  "hide_border": 0,
  "hide_days": 0,
  "hide_seconds": 0,
  "ignore_user_permissions": 0,
  "ignore_xss_filter": 0,
  "in_global_search": 0,
  "in_list_view": 0,
  "in_preview": 0,
  "in_standard_filter": 0,
  "insert_after": "membership_dues_section",
  "is_system_generated": 1,
  "is_virtual": 0,
  "label": "Membership Dues Schedule",
  "length": 0,
  "link_filters": null,
  "mandatory_depends_on": null,
  "modified": "2025-07-27 21:55:32.984163",
  "module": "Verenigingen",
  "name": "Sales Invoice-custom_membership_dues_schedule",
  "no_copy": 0,
  "non_negative": 0,
  "options": "Membership Dues Schedule",
  "permlevel": 0,
  "placeholder": null,
  "precision": "",
  "print_hide": 0,
  "print_hide_if_no_value": 0,
  "print_width": null,
  "read_only": 0,
  "read_only_depends_on": null,
  "report_hide": 0,
  "reqd": 0,
  "search_index": 0,
  "show_dashboard": 0,
  "sort_options": 0,
  "translatable": 0,
  "unique": 0,
  "width": null
 },
 {
  "allow_in_quick_entry": 0,
  "allow_on_submit": 0,
  "bold": 0,
  "collapsible": 0,
  "collapsible_depends_on": null,
  "columns": 0,
  "default": null,
  "depends_on": null,
  "description": null,
  "docstatus": 0,
  "doctype": "Custom Field",
  "dt": "Sales Invoice",
  "fetch_from": null,
  "fetch_if_empty": 0,
  "fieldname": "custom_contribution_mode",
  "fieldtype": "Data",
  "hidden": 0,
  "hide_border": 0,
  "hide_days": 0,
  "hide_seconds": 0,
  "ignore_user_permissions": 0,
  "ignore_xss_filter": 0,
  "in_global_search": 0,
  "in_list_view": 0,
  "in_preview": 0,
  "in_standard_filter": 0,
  "insert_after": "dues_schedule_column_break",
  "is_system_generated": 1,
  "is_virtual": 0,
  "label": "Contribution Mode",
  "length": 0,
  "link_filters": null,
  "mandatory_depends_on": null,
  "modified": "2025-07-27 21:55:32.983596",
  "module": "Verenigingen",
  "name": "Sales Invoice-custom_contribution_mode",
  "no_copy": 0,
  "non_negative": 0,
  "options": null,
  "permlevel": 0,
  "placeholder": null,
  "precision": "",
  "print_hide": 0,
  "print_hide_if_no_value": 0,
  "print_width": null,
  "read_only": 1,
  "read_only_depends_on": null,
  "report_hide": 0,
  "reqd": 0,
  "search_index": 0,
  "show_dashboard": 0,
  "sort_options": 0,
  "translatable": 0,
  "unique": 0,
  "width": null
 },
 {
  "allow_in_quick_entry": 0,
  "allow_on_submit": 0,
  "bold": 0,
  "collapsible": 0,
  "collapsible_depends_on": null,
  "columns": 0,
  "default": null,
  "depends_on": null,
  "description": null,
  "docstatus": 0,
  "doctype": "Custom Field",
  "dt": "Sales Invoice",
  "fetch_from": null,
  "fetch_if_empty": 0,
  "fieldname": "custom_coverage_start_date",
  "fieldtype": "Date",
  "hidden": 0,
  "hide_border": 0,
  "hide_days": 0,
  "hide_seconds": 0,
  "ignore_user_permissions": 0,
  "ignore_xss_filter": 0,
  "in_global_search": 0,
  "in_list_view": 0,
  "in_preview": 0,
  "in_standard_filter": 0,
  "insert_after": "coverage_period_section",
  "is_system_generated": 1,
  "is_virtual": 0,
  "label": "Coverage Start Date",
  "length": 0,
  "link_filters": null,
  "mandatory_depends_on": null,
  "modified": "2025-07-27 21:55:32.981455",
  "module": "Verenigingen",
  "name": "Sales Invoice-custom_coverage_start_date",
  "no_copy": 0,
  "non_negative": 0,
  "options": null,
  "permlevel": 0,
  "placeholder": null,
  "precision": "",
  "print_hide": 0,
  "print_hide_if_no_value": 0,
  "print_width": null,
  "read_only": 0,
  "read_only_depends_on": null,
  "report_hide": 0,
  "reqd": 0,
  "search_index": 0,
  "show_dashboard": 0,
  "sort_options": 0,
  "translatable": 0,
  "unique": 0,
  "width": null
 },
 {
  "allow_in_quick_entry": 0,
  "allow_on_submit": 0,
  "bold": 0,
  "collapsible": 0,
  "collapsible_depends_on": null,
  "columns": 0,
  "default": null,
  "depends_on": null,
  "description": null,
  "docstatus": 0,
  "doctype": "Custom Field",
  "dt": "Sales Invoice",
  "fetch_from": null,
  "fetch_if_empty": 0,
  "fieldname": "custom_coverage_end_date",
  "fieldtype": "Date",
  "hidden": 0,
  "hide_border": 0,
  "hide_days": 0,
  "hide_seconds": 0,
  "ignore_user_permissions": 0,
  "ignore_xss_filter": 0,
  "in_global_search": 0,
  "in_list_view": 0,
  "in_preview": 0,
  "in_standard_filter": 0,
  "insert_after": "coverage_period_column_break",
  "is_system_generated": 1,
  "is_virtual": 0,
  "label": "Coverage End Date",
  "length": 0,
  "link_filters": null,
  "mandatory_depends_on": null,
  "modified": "2025-07-27 21:55:32.980765",
  "module": "Verenigingen",
  "name": "Sales Invoice-custom_coverage_end_date",
  "no_copy": 0,
  "non_negative": 0,
  "options": null,
  "permlevel": 0,
  "placeholder": null,
  "precision": "",
  "print_hide": 0,
  "print_hide_if_no_value": 0,
  "print_width": null,
  "read_only": 0,
  "read_only_depends_on": null,
  "report_hide": 0,
  "reqd": 0,
  "search_index": 0,
  "show_dashboard": 0,
  "sort_options": 0,
  "translatable": 0,
  "unique": 0,
  "width": null
 },
 {
  "allow_in_quick_entry": 0,
  "allow_on_submit": 0,
  "bold": 0,
  "collapsible": 0,
  "collapsible_depends_on": null,
  "columns": 0,
  "default": null,
  "depends_on": null,
  "description": "If this invoice is paid by someone other than the member (e.g., parent, spouse)",
  "docstatus": 0,
  "doctype": "Custom Field",
  "dt": "Sales Invoice",
  "fetch_from": null,
  "fetch_if_empty": 0,
  "fieldname": "custom_paying_for_member",
  "fieldtype": "Link",
  "hidden": 0,
  "hide_border": 0,
  "hide_days": 0,
  "hide_seconds": 0,
  "ignore_user_permissions": 0,
  "ignore_xss_filter": 0,
  "in_global_search": 0,
  "in_list_view": 0,
  "in_preview": 0,
  "in_standard_filter": 0,
  "insert_after": "partner_payment_section",
  "is_system_generated": 1,
  "is_virtual": 0,
  "label": "Paying for Member",
  "length": 0,
  "link_filters": null,
  "mandatory_depends_on": null,
  "modified": "2025-07-27 21:55:32.980133",
  "module": "Verenigingen",
  "name": "Sales Invoice-custom_paying_for_member",
  "no_copy": 0,
  "non_negative": 0,
  "options": "Member",
  "permlevel": 0,
  "placeholder": null,
  "precision": "",
  "print_hide": 0,
  "print_hide_if_no_value": 0,
  "print_width": null,
  "read_only": 0,
  "read_only_depends_on": null,
  "report_hide": 0,
  "reqd": 0,
  "search_index": 0,
  "show_dashboard": 0,
  "sort_options": 0,
  "translatable": 0,
  "unique": 0,
  "width": null
 },
 {
  "allow_in_quick_entry": 0,
  "allow_on_submit": 0,
  "bold": 0,
  "collapsible": 0,
  "collapsible_depends_on": null,
  "columns": 0,
  "default": null,
  "depends_on": "eval:doc.custom_paying_for_member",
  "description": null,
  "docstatus": 0,
  "doctype": "Custom Field",
  "dt": "Sales Invoice",
  "fetch_from": null,
  "fetch_if_empty": 0,
  "fieldname": "custom_payment_relationship",
  "fieldtype": "Select",
  "hidden": 0,
  "hide_border": 0,
  "hide_days": 0,
  "hide_seconds": 0,
  "ignore_user_permissions": 0,
  "ignore_xss_filter": 0,
  "in_global_search": 0,
  "in_list_view": 0,
  "in_preview": 0,
  "in_standard_filter": 0,
  "insert_after": "partner_payment_column_break",
  "is_system_generated": 1,
  "is_virtual": 0,
  "label": "Payment Relationship",
  "length": 0,
  "link_filters": null,
  "mandatory_depends_on": null,
  "modified": "2025-07-27 21:55:32.968661",
  "module": "Verenigingen",
  "name": "Sales Invoice-custom_payment_relationship",
  "no_copy": 0,
  "non_negative": 0,
  "options": "\nParent\nSpouse\nPartner\nGuardian\nOther Family Member\nOrganization\nOther",
  "permlevel": 0,
  "placeholder": null,
  "precision": "",
  "print_hide": 0,
  "print_hide_if_no_value": 0,
  "print_width": null,
  "read_only": 0,
  "read_only_depends_on": null,
  "report_hide": 0,
  "reqd": 0,
  "search_index": 0,
  "show_dashboard": 0,
  "sort_options": 0,
  "translatable": 0,
  "unique": 0,
  "width": null
 },
 {
  "allow_in_quick_entry": 0,
  "allow_on_submit": 0,
  "bold": 0,
  "collapsible": 0,
  "collapsible_depends_on": null,
  "columns": 0,
  "default": null,
  "depends_on": null,
  "description": "Direct link to the associated Member record",
  "docstatus": 0,
  "doctype": "Custom Field",
  "dt": "Customer",
  "fetch_from": null,
  "fetch_if_empty": 0,
  "fieldname": "member",
  "fieldtype": "Link",
  "hidden": 0,
  "hide_border": 0,
  "hide_days": 0,
  "hide_seconds": 0,
  "ignore_user_permissions": 0,
  "ignore_xss_filter": 0,
  "in_global_search": 1,
  "in_list_view": 1,
  "in_preview": 1,
  "in_standard_filter": 1,
  "insert_after": "customer_name",
  "is_system_generated": 0,
  "is_virtual": 0,
  "label": "Member",
  "length": 0,
  "link_filters": null,
  "mandatory_depends_on": null,
  "modified": "2025-01-20 12:00:00",
  "module": "Verenigingen",
  "name": "Customer-member",
  "no_copy": 0,
  "non_negative": 0,
  "options": "Member",
  "permlevel": 0,
  "placeholder": null,
  "precision": "",
  "print_hide": 0,
  "print_hide_if_no_value": 0,
  "print_width": null,
  "read_only": 0,
  "read_only_depends_on": null,
  "report_hide": 0,
  "reqd": 0,
  "search_index": 1,
  "show_dashboard": 1,
  "sort_options": 0,
  "translatable": 0,
  "unique": 1,
  "width": null
 },
 {
  "allow_in_quick_entry": 0,
  "allow_on_submit": 0,
  "bold": 0,
  "collapsible": 0,
  "collapsible_depends_on": null,
  "columns": 0,
  "default": null,
  "depends_on": null,
  "description": "Account number from E-Boekhouden system",
  "docstatus": 0,
  "doctype": "Custom Field",
  "dt": "Account",
  "fetch_from": null,
  "fetch_if_empty": 0,
  "fieldname": "eboekhouden_grootboek_nummer",
  "fieldtype": "Data",
  "hidden": 0,
  "hide_border": 0,
  "hide_days": 0,
  "hide_seconds": 0,
  "ignore_user_permissions": 0,
  "ignore_xss_filter": 0,
  "in_global_search": 0,
  "in_list_view": 0,
  "in_preview": 0,
  "in_standard_filter": 0,
  "insert_after": "account_number",
  "is_system_generated": 0,
  "is_virtual": 0,
  "label": "E-Boekhouden Account Number",
  "length": 0,
  "link_filters": null,
  "mandatory_depends_on": null,
  "modified": "2025-01-02 12:00:00",
  "module": "Verenigingen",
  "name": "Account-eboekhouden_grootboek_nummer",
  "no_copy": 0,
  "non_negative": 0,
  "options": null,
  "permlevel": 0,
  "placeholder": null,
  "precision": "",
  "print_hide": 0,
  "print_hide_if_no_value": 0,
  "print_width": null,
  "read_only": 0,
  "read_only_depends_on": null,
  "report_hide": 0,
  "reqd": 0,
  "search_index": 1,
  "show_dashboard": 0,
  "sort_options": 0,
  "translatable": 0,
  "unique": 0,
  "width": null
 },
 {
  "allow_in_quick_entry": 0,
  "allow_on_submit": 0,
  "bold": 0,
  "collapsible": 0,
  "collapsible_depends_on": null,
  "columns": 0,
  "default": null,
  "depends_on": null,
  "description": "E-Boekhouden mutation number for tracking",
  "docstatus": 0,
  "doctype": "Custom Field",
  "dt": "Purchase Invoice",
  "fetch_from": null,
  "fetch_if_empty": 0,
  "fieldname": "eboekhouden_mutation_nr",
  "fieldtype": "Data",
  "hidden": 0,
  "hide_border": 0,
  "hide_days": 0,
  "hide_seconds": 0,
  "ignore_user_permissions": 0,
  "ignore_xss_filter": 0,
  "in_global_search": 0,
  "in_list_view": 0,
  "in_preview": 0,
  "in_standard_filter": 0,
  "insert_after": "cost_center",
  "is_system_generated": 1,
  "is_virtual": 0,
  "label": "E-Boekhouden Mutation Nr",
  "length": 0,
  "link_filters": null,
  "mandatory_depends_on": null,
  "modified": "2025-08-03 07:24:12.486588",
  "module": "E-Boekhouden",
  "name": "Purchase Invoice-eboekhouden_mutation_nr",
  "no_copy": 0,
  "non_negative": 0,
  "options": null,
  "permlevel": 0,
  "placeholder": null,
  "precision": "",
  "print_hide": 0,
  "print_hide_if_no_value": 0,
  "print_width": null,
  "read_only": 1,
  "read_only_depends_on": null,
  "report_hide": 0,
  "reqd": 0,
  "search_index": 0,
  "show_dashboard": 0,
  "sort_options": 0,
  "translatable": 0,
  "unique": 1,
  "width": null
 },
 {
  "allow_in_quick_entry": 0,
  "allow_on_submit": 0,
  "bold": 0,
  "collapsible": 0,
  "collapsible_depends_on": null,
  "columns": 0,
  "default": null,
  "depends_on": null,
  "description": "E-Boekhouden mutation number for tracking",
  "docstatus": 0,
  "doctype": "Custom Field",
  "dt": "Sales Invoice",
  "fetch_from": null,
  "fetch_if_empty": 0,
  "fieldname": "eboekhouden_mutation_nr",
  "fieldtype": "Data",
  "hidden": 0,
  "hide_border": 0,
  "hide_days": 0,
  "hide_seconds": 0,
  "ignore_user_permissions": 0,
  "ignore_xss_filter": 0,
  "in_global_search": 0,
  "in_list_view": 0,
  "in_preview": 0,
  "in_standard_filter": 0,
  "insert_after": "cost_center",
  "is_system_generated": 1,
  "is_virtual": 0,
  "label": "E-Boekhouden Mutation Nr",
  "length": 0,
  "link_filters": null,
  "mandatory_depends_on": null,
  "modified": "2025-08-03 07:24:03.180603",
  "module": "E-Boekhouden",
  "name": "Sales Invoice-eboekhouden_mutation_nr",
  "no_copy": 0,
  "non_negative": 0,
  "options": null,
  "permlevel": 0,
  "placeholder": null,
  "precision": "",
  "print_hide": 0,
  "print_hide_if_no_value": 0,
  "print_width": null,
  "read_only": 1,
  "read_only_depends_on": null,
  "report_hide": 0,
  "reqd": 0,
  "search_index": 0,
  "show_dashboard": 0,
  "sort_options": 0,
  "translatable": 0,
  "unique": 1,
  "width": null
 },
 {
  "allow_in_quick_entry": 0,
  "allow_on_submit": 1,
  "bold": 0,
  "collapsible": 0,
  "collapsible_depends_on": null,
  "columns": 0,
  "default": null,
  "depends_on": null,
  "description": "E-Boekhouden mutation number for tracking",
  "docstatus": 0,
  "doctype": "Custom Field",
  "dt": "Journal Entry",
  "fetch_from": null,
  "fetch_if_empty": 0,
  "fieldname": "eboekhouden_mutation_nr",
  "fieldtype": "Data",
  "hidden": 0,
  "hide_border": 0,
  "hide_days": 0,
  "hide_seconds": 0,
  "ignore_user_permissions": 0,
  "ignore_xss_filter": 0,
  "in_global_search": 0,
  "in_list_view": 0,
  "in_preview": 0,
  "in_standard_filter": 0,
  "insert_after": "naming_series",
  "is_system_generated": 1,
  "is_virtual": 0,
  "label": "E-Boekhouden Mutation Number",
  "length": 0,
  "link_filters": null,
  "mandatory_depends_on": null,
  "modified": "2025-08-01 20:29:01.930943",
  "module": "E-Boekhouden",
  "name": "Journal Entry-eboekhouden_mutation_nr",
  "no_copy": 0,
  "non_negative": 0,
  "options": null,
  "permlevel": 0,
  "placeholder": null,
  "precision": "",
  "print_hide": 0,
  "print_hide_if_no_value": 0,
  "print_width": null,
  "read_only": 1,
  "read_only_depends_on": null,
  "report_hide": 0,
  "reqd": 0,
  "search_index": 0,
  "show_dashboard": 0,
  "sort_options": 0,
  "translatable": 0,
  "unique": 1,
  "width": null
 },
 {
  "allow_in_quick_entry": 0,
  "allow_on_submit": 1,
  "bold": 0,
  "collapsible": 0,
  "collapsible_depends_on": null,
  "columns": 0,
  "default": null,
  "depends_on": null,
  "description": null,
  "docstatus": 0,
  "doctype": "Custom Field",
  "dt": "Purchase Invoice",
  "fetch_from": null,
  "fetch_if_empty": 0,
  "fieldname": "eboekhouden_invoice_number",
  "fieldtype": "Data",
  "hidden": 0,
  "hide_border": 0,
  "hide_days": 0,
  "hide_seconds": 0,
  "ignore_user_permissions": 0,
  "ignore_xss_filter": 0,
  "in_global_search": 0,
  "in_list_view": 0,
  "in_preview": 0,
  "in_standard_filter": 0,
  "insert_after": "naming_series",
  "is_system_generated": 1,
  "is_virtual": 0,
  "label": "E-Boekhouden Invoice Number",
  "length": 0,
  "link_filters": null,
  "mandatory_depends_on": null,
  "modified": "2025-08-01 20:29:01.901687",
  "module": "E-Boekhouden",
  "name": "Purchase Invoice-eboekhouden_invoice_number",
  "no_copy": 0,
  "non_negative": 0,
  "options": null,
  "permlevel": 0,
  "placeholder": null,
  "precision": "",
  "print_hide": 0,
  "print_hide_if_no_value": 0,
  "print_width": null,
  "read_only": 0,
  "read_only_depends_on": null,
  "report_hide": 0,
  "reqd": 0,
  "search_index": 0,
  "show_dashboard": 0,
  "sort_options": 0,
  "translatable": 0,
  "unique": 1,
  "width": null
 },
 {
  "allow_in_quick_entry": 0,
  "allow_on_submit": 1,
  "bold": 0,
  "collapsible": 0,
  "collapsible_depends_on": null,
  "columns": 0,
  "default": null,
  "depends_on": null,
  "description": null,
  "docstatus": 0,
  "doctype": "Custom Field",
  "dt": "Sales Invoice",
  "fetch_from": null,
  "fetch_if_empty": 0,
  "fieldname": "eboekhouden_invoice_number",
  "fieldtype": "Data",
  "hidden": 0,
  "hide_border": 0,
  "hide_days": 0,
  "hide_seconds": 0,
  "ignore_user_permissions": 0,
  "ignore_xss_filter": 0,
  "in_global_search": 0,
  "in_list_view": 0,
  "in_preview": 0,
  "in_standard_filter": 0,
  "insert_after": "naming_series",
  "is_system_generated": 1,
  "is_virtual": 0,
  "label": "E-Boekhouden Invoice Number",
  "length": 0,
  "link_filters": null,
  "mandatory_depends_on": null,
  "modified": "2025-08-01 20:29:01.630371",
  "module": "E-Boekhouden",
  "name": "Sales Invoice-eboekhouden_invoice_number",
  "no_copy": 0,
  "non_negative": 0,
  "options": null,
  "permlevel": 0,
  "placeholder": null,
  "precision": "",
  "print_hide": 0,
  "print_hide_if_no_value": 0,
  "print_width": null,
  "read_only": 0,
  "read_only_depends_on": null,
  "report_hide": 0,
  "reqd": 0,
  "search_index": 0,
  "show_dashboard": 0,
  "sort_options": 0,
  "translatable": 0,
  "unique": 1,
  "width": null
 },
 {
  "allow_in_quick_entry": 0,
  "allow_on_submit": 0,
  "bold": 0,
  "collapsible": 0,
  "collapsible_depends_on": null,
  "columns": 0,
  "default": null,
  "depends_on": null,
  "description": null,
  "docstatus": 0,
  "doctype": "Custom Field",
  "dt": "Supplier",
  "fetch_from": null,
  "fetch_if_empty": 0,
  "fieldname": "eboekhouden_relation_code",
  "fieldtype": "Data",
  "hidden": 0,
  "hide_border": 0,
  "hide_days": 0,
  "hide_seconds": 0,
  "ignore_user_permissions": 0,
  "ignore_xss_filter": 0,
  "in_global_search": 0,
  "in_list_view": 0,
  "in_preview": 0,
  "in_standard_filter": 0,
  "insert_after": "supplier_name",
  "is_system_generated": 1,
  "is_virtual": 0,
  "label": "E-Boekhouden Relation Code",
  "length": 0,
  "link_filters": null,
  "mandatory_depends_on": null,
  "modified": "2025-08-01 20:29:01.913129",
  "module": "E-Boekhouden",
  "name": "Supplier-eboekhouden_relation_code",
  "no_copy": 0,
  "non_negative": 0,
  "options": null,
  "permlevel": 0,
  "placeholder": null,
  "precision": "",
  "print_hide": 0,
  "print_hide_if_no_value": 0,
  "print_width": null,
  "read_only": 0,
  "read_only_depends_on": null,
  "report_hide": 0,
  "reqd": 0,
  "search_index": 0,
  "show_dashboard": 0,
  "sort_options": 0,
  "translatable": 0,
  "unique": 1,
  "width": null
 },
 {
  "allow_in_quick_entry": 0,
  "allow_on_submit": 0,
  "bold": 0,
  "collapsible": 0,
  "collapsible_depends_on": null,
  "columns": 0,
  "default": null,
  "depends_on": null,
  "description": null,
  "docstatus": 0,
  "doctype": "Custom Field",
  "dt": "Customer",
  "fetch_from": null,
  "fetch_if_empty": 0,
  "fieldname": "eboekhouden_relation_code",
  "fieldtype": "Data",
  "hidden": 0,
  "hide_border": 0,
  "hide_days": 0,
  "hide_seconds": 0,
  "ignore_user_permissions": 0,
  "ignore_xss_filter": 0,
  "in_global_search": 0,
  "in_list_view": 0,
  "in_preview": 0,
  "in_standard_filter": 0,
  "insert_after": "customer_name",
  "is_system_generated": 1,
  "is_virtual": 0,
  "label": "E-Boekhouden Relation Code",
  "length": 0,
  "link_filters": null,
  "mandatory_depends_on": null,
  "modified": "2025-08-01 20:29:01.907481",
  "module": "E-Boekhouden",
  "name": "Customer-eboekhouden_relation_code",
  "no_copy": 0,
  "non_negative": 0,
  "options": null,
  "permlevel": 0,
  "placeholder": null,
  "precision": "",
  "print_hide": 0,
  "print_hide_if_no_value": 0,
  "print_width": null,
  "read_only": 0,
  "read_only_depends_on": null,
  "report_hide": 0,
  "reqd": 0,
  "search_index": 0,
  "show_dashboard": 0,
  "sort_options": 0,
  "translatable": 0,
  "unique": 1,
  "width": null
 },
 {
  "allow_in_quick_entry": 0,
  "allow_on_submit": 1,
  "bold": 0,
  "collapsible": 0,
  "collapsible_depends_on": null,
  "columns": 0,
  "default": null,
  "depends_on": null,
  "description": "E-Boekhouden mutation number for tracking",
  "docstatus": 0,
  "doctype": "Custom Field",
  "dt": "Payment Entry",
  "fetch_from": null,
  "fetch_if_empty": 0,
  "fieldname": "eboekhouden_mutation_nr",
  "fieldtype": "Data",
  "hidden": 0,
  "hide_border": 0,
  "hide_days": 0,
  "hide_seconds": 0,
  "ignore_user_permissions": 0,
  "ignore_xss_filter": 0,
  "in_global_search": 0,
  "in_list_view": 0,
  "in_preview": 0,
  "in_standard_filter": 0,
  "insert_after": "naming_series",
  "is_system_generated": 1,
  "is_virtual": 0,
  "label": "E-Boekhouden Mutation Number",
  "length": 0,
  "link_filters": null,
  "mandatory_depends_on": null,
  "modified": "2025-07-07 21:53:39.036959",
  "module": "E-Boekhouden",
  "name": "Payment Entry-eboekhouden_mutation_nr",
  "no_copy": 0,
  "non_negative": 0,
  "options": null,
  "permlevel": 0,
  "placeholder": null,
  "precision": "",
  "print_hide": 0,
  "print_hide_if_no_value": 0,
  "print_width": null,
  "read_only": 1,
  "read_only_depends_on": null,
  "report_hide": 0,
  "reqd": 0,
  "search_index": 0,
  "show_dashboard": 0,
  "sort_options": 0,
  "translatable": 0,
  "unique": 1,
  "width": null
 },
 {
  "allow_in_quick_entry": 0,
  "allow_on_submit": 1,
  "bold": 0,
  "collapsible": 0,
  "collapsible_depends_on": null,
  "columns": 0,
  "default": null,
  "depends_on": null,
  "description": "0=Opening, 1=PurchInv, 2=SalesInv, 3=CustPayment, 4=SuppPayment, 5=MoneyReceived, 6=MoneySent, 7=Memorial",
  "docstatus": 0,
  "doctype": "Custom Field",
  "dt": "Payment Entry",
  "fetch_from": null,
  "fetch_if_empty": 0,
  "fieldname": "eboekhouden_mutation_type",
  "fieldtype": "Select",
  "hidden": 0,
  "hide_border": 0,
  "hide_days": 0,
  "hide_seconds": 0,
  "ignore_user_permissions": 0,
  "ignore_xss_filter": 0,
  "in_global_search": 0,
  "in_list_view": 0,
  "in_preview": 0,
  "in_standard_filter": 0,
  "insert_after": "eboekhouden_mutation_nr",
  "is_system_generated": 1,
  "is_virtual": 0,
  "label": "E-Boekhouden Mutation Type",
  "length": 0,
  "link_filters": null,
  "mandatory_depends_on": null,
  "modified": "2025-07-15 07:17:53.902807",
  "module": "E-Boekhouden",
  "name": "Payment Entry-eboekhouden_mutation_type",
  "no_copy": 0,
  "non_negative": 0,
  "options": "\n0\n1\n2\n3\n4\n5\n6\n7",
  "permlevel": 0,
  "placeholder": null,
  "precision": "",
  "print_hide": 0,
  "print_hide_if_no_value": 0,
  "print_width": null,
  "read_only": 0,
  "read_only_depends_on": null,
  "report_hide": 0,
  "reqd": 0,
  "search_index": 0,
  "show_dashboard": 0,
  "sort_options": 0,
  "translatable": 0,
  "unique": 0,
  "width": null
 }
]
